agentrl/eval/__init__.py
agentrl/eval/__main__.py
agentrl/eval/_version.py
agentrl/eval/cli/__init__.py
agentrl/eval/cli/main.py
agentrl/eval/cli/settings.py
agentrl/eval/cli/tui.py
agentrl/eval/client/__init__.py
agentrl/eval/client/_base.py
agentrl/eval/client/_create.py
agentrl/eval/client/anthropic.py
agentrl/eval/client/dummy.py
agentrl/eval/client/openai.py
agentrl/eval/convert/__init__.py
agentrl/eval/convert/_base.py
agentrl/eval/convert/messages.py
agentrl/eval/convert/tools.py
agentrl/eval/event/__init__.py
agentrl/eval/event/bus.py
agentrl/eval/event/types.py
agentrl/eval/session/__init__.py
agentrl/eval/session/controller.py
agentrl/eval/session/metric.py
agentrl/eval/session/runner.py
agentrl/eval/session/tokens.py
agentrl/eval/session/types.py
agentrl/eval/session/workflow.py
agentrl/eval/store/__init__.py
agentrl/eval/store/list.py
agentrl/eval/store/store.py
agentrl/eval/store/types.py
agentrl/eval/utils/__init__.py
agentrl/eval/utils/data_url.py
agentrl/eval/utils/logging.py
agentrl/eval/utils/messages.py
agentrl/eval/utils/utils.py
agentrl_eval-0.1.2.dist-info/METADATA
agentrl_eval-0.1.2.dist-info/WHEEL
agentrl_eval-0.1.2.dist-info/entry_points.txt
agentrl_eval-0.1.2.dist-info/top_level.txt
agentrl_eval-0.1.2.dist-info/RECORD
