Metadata-Version: 2.4
Name: agentrl-eval
Version: 0.1.2
Summary: Evaluation client of AgentRL: Scaling Agentic Reinforcement Learning with a Multi-Turn, Multi-Task Framework
License-Expression: MIT
Project-URL: Repository, https://github.com/THUDM/AgentRL
Project-URL: Issues, https://github.com/THUDM/AgentRL/issues
Classifier: Operating System :: OS Independent
Classifier: Programming Language :: Python :: 3
Classifier: Typing :: Typed
Requires-Python: >=3.10
Requires-Dist: anthropic[bedrock]
Requires-Dist: httpx[http2,socks]
Requires-Dist: openai~=2.0
Requires-Dist: polars[async]
Requires-Dist: Pillow
Requires-Dist: pydantic-settings
Provides-Extra: tui
Requires-Dist: rich; extra == "tui"
Requires-Dist: textual; extra == "tui"
Provides-Extra: dev
Requires-Dist: pytest; extra == "dev"
Requires-Dist: pytest-cov; extra == "dev"
Requires-Dist: textual-dev; extra == "dev"
